CHANGES.txt
CONTRIBUTORS.txt
MANIFEST.in
README.txt
TODO
setup.cfg
setup.py
docs/HISTORY.txt
docs/INSTALL.txt
docs/LICENSE.GPL
docs/LICENSE.txt
plumi/__init__.py
plumi.migration.egg-info/PKG-INFO
plumi.migration.egg-info/SOURCES.txt
plumi.migration.egg-info/dependency_links.txt
plumi.migration.egg-info/entry_points.txt
plumi.migration.egg-info/namespace_packages.txt
plumi.migration.egg-info/not-zip-safe
plumi.migration.egg-info/paster_plugins.txt
plumi.migration.egg-info/requires.txt
plumi.migration.egg-info/top_level.txt
plumi/migration/README.txt
plumi/migration/__init__.py
plumi/migration/config.py
plumi/migration/configure.zcml
plumi/migration/members_csv.py
plumi/migration/setuphandlers.py
plumi/migration/version.txt
plumi/migration/browser/__init__.py
plumi/migration/browser/config.py
plumi/migration/browser/configure.zcml
plumi/migration/content/__init__.py
plumi/migration/content/configure.zcml
plumi/migration/interfaces/__init__.py
plumi/migration/interfaces/migration.py
plumi/migration/portlets/__init__.py
plumi/migration/portlets/configure.zcml
plumi/migration/profiles/default/controlpanel.xml
plumi/migration/profiles/default/factorytool.xml
plumi/migration/profiles/default/import_steps.xml
plumi/migration/profiles/default/metadata.xml
plumi/migration/profiles/default/plumi.migration_various.txt
plumi/migration/profiles/default/portlets.xml
plumi/migration/profiles/default/types.xml
plumi/migration/tests/__init__.py
plumi/migration/tests/base.py
plumi/migration/tests/test_doctest.py