Metadata-Version: 1.0
Name: plumi.migration
Version: 0.5
Summary: Migration for Plumi 0.2.x sites to Plumi 3.0 sites
Home-page: http://plumi.org/
Author: Andy Nicholson
Author-email: andy@infiniterecursion.com.au
License: GPLv3
Keywords: web zope plone plumi
Platform: UNKNOWN
Classifier: Framework :: Plone
Classifier: Intended Audience :: Developers
Classifier: Topic :: Software Development :: Libraries :: Python Modules
